EXAMPLE_PIZZAVARS
LICENSE
MANIFEST.in
README.md
setup.py
pizzabutton/__init__.py
pizzabutton/pizza_utils.py
pizzabutton.egg-info/PKG-INFO
pizzabutton.egg-info/SOURCES.txt
pizzabutton.egg-info/dependency_links.txt
pizzabutton.egg-info/requires.txt
pizzabutton.egg-info/top_level.txt
pizzabutton/static/index.js