Metadata-Version: 1.0
Name: pizzabutton
Version: 0.0.5
Summary: A button on Jupyter's toolbar for pizza
Home-page: https://github.com/peterskipper/pizzabutton
Author: Peter Skipper
Author-email: peter.skipper@gmail.com
License: UNKNOWN
Platform: UNKNOWN
